tr_rosetta_pytorch/__init__.py
tr_rosetta_pytorch/cli.py
tr_rosetta_pytorch/tr_rosetta_pytorch.py
tr_rosetta_pytorch/utils.py
tr_rosetta_pytorch/models/models.tar.gz
tr_rosetta_pytorch-0.0.3.dist-info/LICENSE
tr_rosetta_pytorch-0.0.3.dist-info/METADATA
tr_rosetta_pytorch-0.0.3.dist-info/WHEEL
tr_rosetta_pytorch-0.0.3.dist-info/entry_points.txt
tr_rosetta_pytorch-0.0.3.dist-info/top_level.txt
tr_rosetta_pytorch-0.0.3.dist-info/RECORD
