Metadata-Version: 2.1
Name: tr-rosetta-pytorch
Version: 0.0.3
Summary: trRosetta - Pytorch
Home-page: https://github.com/lucidrains/tr-rosetta-pytorch
Author: Phil Wang
Author-email: lucidrains@gmail.com
License: MIT
Keywords: artificial intelligence,protein folding,protein design
Platform: UNKNOWN
Classifier: Development Status :: 4 - Beta
Classifier: Intended Audience :: Developers
Classifier: Topic :: Scientific/Engineering :: Artificial Intelligence
Classifier: License :: OSI Approved :: MIT License
Classifier: Programming Language :: Python :: 3.6
Requires-Dist: einops (>=0.3)
Requires-Dist: fire
Requires-Dist: numpy
Requires-Dist: torch (>=1.6)
